fruitgenerator/__init__.py
fruitgenerator/generator.py
fruitgenerator-0.1.dist-info/METADATA
fruitgenerator-0.1.dist-info/WHEEL
fruitgenerator-0.1.dist-info/top_level.txt
fruitgenerator-0.1.dist-info/RECORD
