Metadata-Version: 2.1
Name: fruitgenerator
Version: 0.1
Summary: Generate fruit names based on user input
Author: Your Name
